jamurai.py
jamurai-0.1.3.dist-info/LICENSE.txt
jamurai-0.1.3.dist-info/METADATA
jamurai-0.1.3.dist-info/WHEEL
jamurai-0.1.3.dist-info/top_level.txt
jamurai-0.1.3.dist-info/RECORD
