Metadata-Version: 2.1
Name: jamurai
Version: 0.1.3
Summary: Jinja wrapper for file and directory transformation and injection
Home-page: https://jamurai.readthedocs.io/en/0.1.3/
Download-URL: https://github.com/gaf3/jamurai
Author: Gaffer Fitch
Author-email: jamurai@gaf3.com
Classifier: Programming Language :: Python :: 3
Classifier: License :: OSI Approved :: MIT License
License-File: LICENSE.txt
Requires-Dist: Jinja2==3.1.2
Requires-Dist: overscore==0.1.2
Requires-Dist: yaes>=0.2.5
Requires-Dist: PyYAML==6.0.1
Requires-Dist: MarkupSafe==2.1.5
